jsx/__init__.py
jsx/lexer.py
jsx_lexer-2.0.1.dist-info/LICENSE
jsx_lexer-2.0.1.dist-info/METADATA
jsx_lexer-2.0.1.dist-info/WHEEL
jsx_lexer-2.0.1.dist-info/entry_points.txt
jsx_lexer-2.0.1.dist-info/top_level.txt
jsx_lexer-2.0.1.dist-info/RECORD
