Metadata-Version: 2.1
Name: jsx-lexer
Version: 2.0.1
Summary: A JSX lexer for Pygments
Home-page: https://github.com/fcurella/jsx-lexer
Author: Flavio Curella
Author-email: flavio.curella@gmail.com
License: MIT License
Keywords: pygments highlight jsx react
Classifier: Environment :: Plugins
Classifier: Intended Audience :: Developers
Classifier: Programming Language :: Python :: 3
License-File: LICENSE
Requires-Dist: Pygments (>=2.12.0)
